README.md
setup.cfg
setup.py
src/ExpdGetFolderFiles/__init__.py
src/ExpdGetFolderFiles.egg-info/PKG-INFO
src/ExpdGetFolderFiles.egg-info/SOURCES.txt
src/ExpdGetFolderFiles.egg-info/dependency_links.txt
src/ExpdGetFolderFiles.egg-info/requires.txt
src/ExpdGetFolderFiles.egg-info/top_level.txt